MANIFEST.in
setup.py
dj_admin_bootstrapped/__init__.py
dj_admin_bootstrapped/models.py
dj_admin_bootstrapped/widgets.py
dj_admin_bootstrapped.egg-info/PKG-INFO
dj_admin_bootstrapped.egg-info/SOURCES.txt
dj_admin_bootstrapped.egg-info/dependency_links.txt
dj_admin_bootstrapped.egg-info/not-zip-safe
dj_admin_bootstrapped.egg-info/requires.txt
dj_admin_bootstrapped.egg-info/top_level.txt
dj_admin_bootstrapped/admin/__init__.py
dj_admin_bootstrapped/admin/models.py
dj_admin_bootstrapped/static/.DS_Store
dj_admin_bootstrapped/static/bootstrap/css/bootstrap-theme.css
dj_admin_bootstrapped/static/bootstrap/css/bootstrap-theme.min.css
dj_admin_bootstrapped/static/bootstrap/css/bootstrap.css
dj_admin_bootstrapped/static/bootstrap/css/bootstrap.min.css
dj_admin_bootstrapped/static/bootstrap/css/general.css
dj_admin_bootstrapped/static/bootstrap/fonts/glyphicons-halflings-regular.eot
dj_admin_bootstrapped/static/bootstrap/fonts/glyphicons-halflings-regular.svg
dj_admin_bootstrapped/static/bootstrap/fonts/glyphicons-halflings-regular.ttf
dj_admin_bootstrapped/static/bootstrap/fonts/glyphicons-halflings-regular.woff
dj_admin_bootstrapped/static/bootstrap/js/bootstrap.js
dj_admin_bootstrapped/static/bootstrap/js/bootstrap.min.js
dj_admin_bootstrapped/static/css/blueberry.css
dj_admin_bootstrapped/static/css/bootstrap.css
dj_admin_bootstrapped/static/css/bootstrap.min.css
dj_admin_bootstrapped/static/css/carousel.css
dj_admin_bootstrapped/static/css/contactenos.css
dj_admin_bootstrapped/static/css/datetimepicker.css
dj_admin_bootstrapped/static/css/demo.css
dj_admin_bootstrapped/static/css/dj_admin_bootstrapped.css
dj_admin_bootstrapped/static/css/forms.css
dj_admin_bootstrapped/static/css/jquery.jscrollpane.css
dj_admin_bootstrapped/static/css/least.min.css
dj_admin_bootstrapped/static/css/least.scss
dj_admin_bootstrapped/static/css/m2m.css
dj_admin_bootstrapped/static/css/reset.css
dj_admin_bootstrapped/static/css/scrolling-nav.css
dj_admin_bootstrapped/static/css/style.css
dj_admin_bootstrapped/static/css/theme.css
dj_admin_bootstrapped/static/font-awesome/css/font-awesome.css
dj_admin_bootstrapped/static/font-awesome/css/font-awesome.min.css
dj_admin_bootstrapped/static/font-awesome/fonts/FontAwesome.otf
